hdrive/__init__.py
hdrive/file-info.txt
hdrive-2024.2.13.dist-info/WHEEL
hdrive-2024.2.13.dist-info/METADATA
hdrive-2024.2.13.dist-info/RECORD
