Metadata-Version: 2.1
Name: hdrive
Version: 2024.2.13
Summary: 一个基于 JSON 的键-值存储类。与操作 Python 字典类似，但每次修改后都会自动保存到硬盘
Author-email: 江南雨上 <lcctoor@outlook.com>
